cron_parser.py
mp_cron_parser-0.1.5.dist-info/licenses/LICENSE
mp_cron_parser-0.1.5.dist-info/METADATA
mp_cron_parser-0.1.5.dist-info/WHEEL
mp_cron_parser-0.1.5.dist-info/top_level.txt
mp_cron_parser-0.1.5.dist-info/RECORD
