Metadata-Version: 2.4
Name: mp-cron-parser
Version: 0.1.5
Summary: A lightweight cron expression parser for MicroPython and Python.
Author-email: Aviram Dayan <aviram26@email.com>
License-Expression: MIT
Project-URL: Homepage, https://github.com/aviram26/mp-cron-parser
License-File: LICENSE
Dynamic: license-file
